{
  "schemaVersion": 1,
  "id": "betterstrongholds",
  "version": "${version}",
  "name": "YUNG's Better Strongholds",
  "description": "A complete redesign of Minecraft's strongholds",
  "authors": [
    "YUNGNICKYOUNG",
    "Acarii"
  ],
  "contact": {
    "homepage": "https://www.curseforge.com/minecraft/mc-mods/yungs-better-strongholds-fabric",
    "sources": "https://github.com/yungnickyoung/YUNGs-Better-Strongholds",
    "issues": "https://github.com/yungnickyoung/YUNGs-Better-Strongholds/issues",
    "discord": "discord.gg/rns3beq"
  },
  "license": "LGPLv3",
  "icon": "assets/betterstrongholds/logo_sm.png",
  "environment": "*",
  "entrypoints": {
    "main": [
      "com.yungnickyoung.minecraft.betterstrongholds.BetterStrongholds"
    ],
    "client": [
      "com.yungnickyoung.minecraft.betterstrongholds.BetterStrongholds"
    ],
    "server": [
      "com.yungnickyoung.minecraft.betterstrongholds.BetterStrongholds"
    ],
    "modmenu": [
      "com.yungnickyoung.minecraft.betterstrongholds.config.gui.BSModMenu"
    ]
  },
  "mixins": [
    "betterstrongholds.mixins.json"
  ],
  "accessWidener": "betterstrongholds.aw",
  "depends": {
    "fabricloader": ">=0.10.6",
    "fabric": ">=0.33.0+1.16",
    "minecraft": ">=1.16.4",
    "yungsapi": ">=1.16.5-Fabric-7"
  }
}